ul_db_utils/__init__.py
ul_db_utils/conf.py
ul_db_utils/main.py
ul_db_utils/py.typed
ul_db_utils/commands/__init__.py
ul_db_utils/commands/cmd_action.py
ul_db_utils/commands/cmd_docs.py
ul_db_utils/commands/cmd_dump.py
ul_db_utils/commands/cmd_restore.py
ul_db_utils/commands/cmd_waiting.py
ul_db_utils/commands/doc_request_sql.sql
ul_db_utils/errors/__init__.py
ul_db_utils/errors/compare_null_error.py
ul_db_utils/errors/db_error.py
ul_db_utils/errors/db_filter_error.py
ul_db_utils/errors/db_sort_error.py
ul_db_utils/errors/deletion_not_allowed.py
ul_db_utils/errors/multiple_objects_returned.py
ul_db_utils/errors/unknow_field_error.py
ul_db_utils/errors/update_column_not_allowed_error.py
ul_db_utils/errors/update_not_allowed.py
ul_db_utils/model/__init__.py
ul_db_utils/model/api_user.py
ul_db_utils/model/base_api_user_log_model.py
ul_db_utils/model/base_document.py
ul_db_utils/model/base_immutable_model.py
ul_db_utils/model/base_mater_pg_view.py
ul_db_utils/model/base_model.py
ul_db_utils/model/base_undeletable_model.py
ul_db_utils/model/base_undeletable_user_log_model.py
ul_db_utils/model/base_user_log_model.py
ul_db_utils/model/referense_link.py
ul_db_utils/model/media_storage/__init__.py
ul_db_utils/model/media_storage/media_file.py
ul_db_utils/model/media_storage/media_file_download_link.py
ul_db_utils/model/media_storage/media_file_type.py
ul_db_utils/model/methods/__init__.py
ul_db_utils/model/methods/make_immutable_column.py
ul_db_utils/modules/__init__.py
ul_db_utils/modules/audit.sql
ul_db_utils/modules/audit_manager.py
ul_db_utils/modules/custom_query.py
ul_db_utils/modules/db.py
ul_db_utils/modules/db_context.py
ul_db_utils/modules/transaction_commit.py
ul_db_utils/modules/mongo_db_modules/__init__.py
ul_db_utils/modules/mongo_db_modules/db.py
ul_db_utils/modules/mongo_db_modules/db_context.py
ul_db_utils/modules/postgres_modules/__init__.py
ul_db_utils/modules/postgres_modules/custom_query.py
ul_db_utils/modules/postgres_modules/db.py
ul_db_utils-5.1.0.dist-info/LICENSE
ul_db_utils-5.1.0.dist-info/METADATA
ul_db_utils-5.1.0.dist-info/WHEEL
ul_db_utils-5.1.0.dist-info/entry_points.txt
ul_db_utils-5.1.0.dist-info/top_level.txt
ul_db_utils-5.1.0.dist-info/RECORD
