Metadata-Version: 2.1
Name: ul-db-utils
Version: 5.1.0
Summary: Python ul db utils
Home-page: https://gitlab.neroelectronics.by/unic-lab/libraries/common-python-utils/db-utils.git
Author: Unic-lab
Author-email: 
Platform: any
Classifier: Intended Audience :: Developers
Classifier: License :: OSI Approved :: MIT License
Classifier: Programming Language :: Python
Classifier: Programming Language :: Python :: 3.6
Classifier: Programming Language :: Python :: 3.7
Classifier: Programming Language :: Python :: 3.8
Classifier: Programming Language :: Python :: 3.9
Classifier: Operating System :: OS Independent
License-File: LICENSE
Requires-Dist: flask (==3.1.0)
Requires-Dist: py-dateutil (==2.2)
Requires-Dist: psycopg2-binary (==2.9.9)
Requires-Dist: psycogreen (==1.0.2)
Requires-Dist: flask-sqlalchemy (==3.1.1)
Requires-Dist: flask-migrate (==4.1.0)
Requires-Dist: sqlalchemy[mypy] (==2.0.29)
Requires-Dist: sqlalchemy-utils (==0.41.2)
Requires-Dist: sqlalchemy-serializer (==1.4.21)
Requires-Dist: alembic (==1.14.1)
Requires-Dist: flask-mongoengine-3 (==1.1.0)
Requires-Dist: redis (==5.2.1)
Requires-Dist: types-psycopg2 (==2.9.21.20250121)
Requires-Dist: types-sqlalchemy-utils (==1.1.0)
Requires-Dist: ul-py-tool (>=1.15.42)
